[
	{
		"id": 1,
		"name": "牡丹",
		"imageName": "mudan.jpg",
		"subjectID": 5
	}, {
		"id": 2,
		"name": "康乃馨",
		"imageName": "kangnaixin.jpg",
		"subjectID": 5
	}, {
		"id": 3,
		"name": "月季",
		"imageName": "yueji.jpg",
		"subjectID": 5
	}, {
		"id": 4,
		"name": "玫瑰",
		"imageName": "meigui.jpg",
		"subjectID": 5
	}, {
		"id": 5,
		"name": "勿忘我",
		"imageName": "wuwangwo.jpg",
		"subjectID": 5
	}, {
		"id": 6,
		"name": "丁香",
		"imageName": "dingxiang.jpg",
		"subjectID": 5
	}, {
		"id": 7,
		"name": "郁金香",
		"imageName": "yujinxiang.jpg",
		"subjectID": 5
	}, {
		"id": 8,
		"name": "向日葵",
		"imageName": "xiangrikui.jpg",
		"subjectID": 5
	}, {
		"id": 9,
		"name": "兰花",
		"imageName": "lanhua.jpg",
		"subjectID": 5
	}, {
		"id": 10,
		"name": "桃花",
		"imageName": "taohua.jpg",
		"subjectID": 5
	}, {
		"id": 11,
		"name": "牵牛花",
		"imageName": "qianniuhua.jpg",
		"subjectID": 5
	}, {
		"id": 12,
		"name": "海棠",
		"imageName": "haitang.jpg",
		"subjectID": 5
	}, {
		"id": 13,
		"name": "水仙",
		"imageName": "shuixian.jpg",
		"subjectID": 5
	}, {
		"id": 14,
		"name": "马蹄莲",
		"imageName": "matilian.jpg",
		"subjectID": 5
	}, {
		"id": 15,
		"name": "菊花",
		"imageName": "juhua.jpg",
		"subjectID": 5
	}, {
		"id": 16,
		"name": "梅花",
		"imageName": "meihua.jpg",
		"subjectID": 5
	}, {
		"id": 17,
		"name": "百合",
		"imageName": "baihe.jpg",
		"subjectID": 5
	}, {
		"id": 18,
		"name": "荷花",
		"imageName": "hehua.jpg",
		"subjectID": 5
	}, {
		"id": 19,
		"name": "木棉",
		"imageName": "mumian.jpg",
		"subjectID": 5
	}, {
		"id": 20,
		"name": "紫荆花",
		"imageName": "zijinghua.jpg",
		"subjectID": 5
	}, {
		"id": 21,
		"name": "樱花",
		"imageName": "yinghua.jpg",
		"subjectID": 5
	}, {
		"id": 22,
		"name": "梨花",
		"imageName": "lihua.jpg",
		"subjectID": 5
	}, {
		"id": 23,
		"name": "昙花",
		"imageName": "tanhua.jpg",
		"subjectID": 5
	}, {
		"id": 24,
		"name": "石榴花",
		"imageName": "shiliuhua.jpg",
		"subjectID": 5
	}, {
		"id": 25,
		"name": "米兰",
		"imageName": "milan.jpg",
		"subjectID": 5
	}, {
		"id": 26,
		"name": "满天星",
		"imageName": "mantianxing.jpg",
		"subjectID": 5
	}, {
		"id": 27,
		"name": "鸡蛋花",
		"imageName": "jidanhua.jpg",
		"subjectID": 5
	}, {
		"id": 28,
		"name": "山茶花",
		"imageName": "shanchahua.jpg",
		"subjectID": 5
	}, {
		"id": 29,
		"name": "夹竹桃",
		"imageName": "jiazhutao.jpg",
		"subjectID": 5
	}, {
		"id": 30,
		"name": "玉兰花",
		"imageName": "yulanhua.jpg",
		"subjectID": 5
	}, {
		"id": 31,
		"name": "芍药",
		"imageName": "shaoyao.jpg",
		"subjectID": 5
	}, {
		"id": 32,
		"name": "桂花",
		"imageName": "guihua.jpg",
		"subjectID": 5
	}, {
		"id": 33,
		"name": "雪莲花",
		"imageName": "xuelianhua.jpg",
		"subjectID": 5
	}
]